ks_openai/__init__.py
ks_openai/api.py
ks_openai/utils.py
ks_openai-1.0.0.dist-info/licenses/LICENSE
ks_openai-1.0.0.dist-info/METADATA
ks_openai-1.0.0.dist-info/WHEEL
ks_openai-1.0.0.dist-info/top_level.txt
ks_openai-1.0.0.dist-info/RECORD
